.gitignore
LICENSE
README.md
pyproject.toml
setup.cfg
.sourcehut/arch.yml
src/labxdb/__init__.py
src/labxdb/fastq.py
src/labxdb/ncbi.py
src/labxdb_scripts/__init__.py
src/labxdb_scripts/export_sra.py
src/labxdb_scripts/export_sra_fastq.py
src/labxdb_scripts/fastq_strip.py
src/labxdb_scripts/import_seq.py
src/labxdb_scripts/import_sra.py
src/labxdb_scripts/import_sra_id.py
src/labxdb_tools.egg-info/PKG-INFO
src/labxdb_tools.egg-info/SOURCES.txt
src/labxdb_tools.egg-info/dependency_links.txt
src/labxdb_tools.egg-info/entry_points.txt
src/labxdb_tools.egg-info/requires.txt
src/labxdb_tools.egg-info/top_level.txt