Metadata-Version: 2.1
Name: labxdb-tools
Version: 0.7.0
Summary: Versatile databases for genomic sequencing and lab management.
Home-page: https://sr.ht/~vejnar/LabxDB
Author: Charles E. Vejnar
License: Mozilla Public License 2.0 (MPL 2.0)
Requires-Python: >=3.8
License-File: LICENSE
